cywidget/__init__.py
cywidget-1.1.0.data/data/share/jupyter/nbtools/cywidget.json
cywidget-1.1.0.dist-info/LICENSE.md
cywidget-1.1.0.dist-info/METADATA
cywidget-1.1.0.dist-info/WHEEL
cywidget-1.1.0.dist-info/top_level.txt
cywidget-1.1.0.dist-info/RECORD
